mod1.py
mod1/__init__.py
mod1/add.py
mod1/submod/__init__.py
mod1/submod/multi.py
mod2/__init__.py
mod2/sub.py
cnspary_p1-0.0.7.dist-info/METADATA
cnspary_p1-0.0.7.dist-info/WHEEL
cnspary_p1-0.0.7.dist-info/top_level.txt
cnspary_p1-0.0.7.dist-info/RECORD
