Metadata-Version: 2.1
Name: cnspary-p1
Version: 0.0.7
Summary: MC-PackageOne
Home-page: UNKNOWN
Author: cnspary
Author-email: cnspary@outlook.com
License: UNKNOWN
Platform: UNKNOWN
Requires-Python: >=3.0
